panns_inference/__init__.py
panns_inference/config.py
panns_inference/inference.py
panns_inference/models.py
panns_inference/pytorch_utils.py
panns_inference-0.1.1.dist-info/LICENSE.MIT
panns_inference-0.1.1.dist-info/METADATA
panns_inference-0.1.1.dist-info/WHEEL
panns_inference-0.1.1.dist-info/top_level.txt
panns_inference-0.1.1.dist-info/RECORD
