Metadata-Version: 2.1
Name: panns-inference
Version: 0.1.1
Summary: panns_inference: audio tagging and sound event detection inference toolbox
Home-page: https://github.com/qiuqiangkong/panns_inference
Author: Qiuqiang Kong
Author-email: qiuqiangkong@gmail.com
Classifier: Programming Language :: Python :: 3
Classifier: License :: OSI Approved :: MIT License
Classifier: Operating System :: OS Independent
Requires-Python: >=3.6
License-File: LICENSE.MIT
